doguda/__init__.py
doguda/__main__.py
doguda/app.py
doguda/loader.py
doguda-0.1.9.dist-info/licenses/LICENSE
doguda-0.1.9.dist-info/METADATA
doguda-0.1.9.dist-info/WHEEL
doguda-0.1.9.dist-info/entry_points.txt
doguda-0.1.9.dist-info/top_level.txt
doguda-0.1.9.dist-info/RECORD
