Metadata-Version: 2.4
Name: doguda
Version: 0.1.9
Summary: Turn Python functions into CLI commands and HTTP endpoints instantly
Author: cookieshake
License-Expression: MIT
Project-URL: Homepage, https://github.com/cookieshake/doguda
Project-URL: Repository, https://github.com/cookieshake/doguda
Project-URL: Issues, https://github.com/cookieshake/doguda/issues
Keywords: cli,http,fastapi,typer,automation,api,command-line
Classifier: Development Status :: 4 - Beta
Classifier: Environment :: Console
Classifier: Framework :: FastAPI
Classifier: Intended Audience :: Developers
Classifier: Operating System :: OS Independent
Classifier: Programming Language :: Python :: 3
Classifier: Programming Language :: Python :: 3.10
Classifier: Programming Language :: Python :: 3.11
Classifier: Programming Language :: Python :: 3.12
Classifier: Programming Language :: Python :: 3.13
Classifier: Topic :: Software Development :: Libraries :: Python Modules
Classifier: Topic :: Internet :: WWW/HTTP :: HTTP Servers
Classifier: Typing :: Typed
Requires-Python: >=3.10
License-File: LICENSE
Requires-Dist: fastapi>=0.100.0
Requires-Dist: uvicorn>=0.23.0
Requires-Dist: typer>=0.9.0
Requires-Dist: pydantic>=2.0.0
Provides-Extra: dev
Requires-Dist: pytest>=7.0.0; extra == "dev"
Requires-Dist: ruff>=0.1.0; extra == "dev"
Dynamic: license-file
